chronoflex/__init__.py
chronoflex/localization.py
chronoflex/scheduling.py
chronoflex/timezone.py
chronoflex/utils.py
chronoflex-0.1.dist-info/METADATA
chronoflex-0.1.dist-info/WHEEL
chronoflex-0.1.dist-info/top_level.txt
chronoflex-0.1.dist-info/RECORD
